unifyops_core/__init__.py
unifyops_core/client/__init__.py
unifyops_core/client/base_client.py
unifyops_core/exceptions/__init__.py
unifyops_core/exceptions/api.py
unifyops_core/exceptions/base.py
unifyops_core/exceptions/database.py
unifyops_core/exceptions/domain.py
unifyops_core/exceptions/handler.py
unifyops_core/exceptions/http.py
unifyops_core/exceptions/models.py
unifyops_core/exceptions/operational.py
unifyops_core/exceptions/security.py
unifyops_core/exceptions/utils.py
unifyops_core/exceptions/validation.py
unifyops_core/logging/__init__.py
unifyops_core/logging/config.py
unifyops_core/logging/middleware.py
unifyops_core/logging/processors.py
unifyops_core/logging/examples/__init__.py
unifyops_core/logging/examples/quickstart.py
unifyops_core/logging/handlers/__init__.py
unifyops_core/utils/__init__.py
unifyops_core/utils/utils.py
unifyops_core-2.0.0.dist-info/METADATA
unifyops_core-2.0.0.dist-info/WHEEL
unifyops_core-2.0.0.dist-info/top_level.txt
unifyops_core-2.0.0.dist-info/RECORD
