Metadata-Version: 2.4
Name: unifyops-core
Version: 2.0.0
Summary: Core utilities for UnifyOps Python projects
Author-email: UnifyOps Team <admin@unifyops.com>
License-Expression: MIT
Project-URL: Homepage, https://github.com/unifyops/unifyops-core
Project-URL: Repository, https://github.com/unifyops/unifyops-core
Keywords: unifyops,utilities,logging,exceptions,observability
Classifier: Development Status :: 3 - Alpha
Classifier: Intended Audience :: Developers
Classifier: Programming Language :: Python :: 3
Classifier: Programming Language :: Python :: 3.10
Classifier: Programming Language :: Python :: 3.11
Classifier: Programming Language :: Python :: 3.12
Requires-Python: >=3.10
Requires-Dist: pydantic>=2.4.0
Requires-Dist: structlog>=22.1.0
Requires-Dist: python-json-logger>=2.0.0
Requires-Dist: fastapi>=0.100.0
